behave_auto_docstring/__init__.py
behave_auto_docstring/docstring.py
behave_auto_docstring/griffe.py
behave_auto_docstring/test_docstring.py
behave_auto_docstring/test_init.py
behave_auto_docstring/testing.py
behave_auto_docstring-0.1.3.dist-info/METADATA
behave_auto_docstring-0.1.3.dist-info/WHEEL
behave_auto_docstring-0.1.3.dist-info/top_level.txt
behave_auto_docstring-0.1.3.dist-info/RECORD
