Metadata-Version: 2.4
Name: behave-auto-docstring
Version: 0.1.3
Author: Helge
Project-URL: Repository, https://codeberg.org/helge/behave_auto_docstring
Requires-Python: >=3.10
Requires-Dist: behave>=1.3.3
Requires-Dist: griffe>=1.15.0
